sirepo_bluesky/__init__.py
sirepo_bluesky/_version.py
sirepo_bluesky/madx_flyer.py
sirepo_bluesky/madx_handler.py
sirepo_bluesky/shadow_handler.py
sirepo_bluesky/sirepo_bluesky.py
sirepo_bluesky/sirepo_flyer.py
sirepo_bluesky/sirepo_ophyd.py
sirepo_bluesky/srw_handler.py
sirepo_bluesky/tests/__init__.py
sirepo_bluesky/tests/conftest.py
sirepo_bluesky/tests/test_bl_elements_as_ophyd_objs.py
sirepo_bluesky/tests/test_converter.py
sirepo_bluesky/tests/test_sirepo_flyer.py
sirepo_bluesky/tests/test_stateless_compute.py
sirepo_bluesky/utils/__init__.py
sirepo_bluesky/utils/json_yaml_converter.py
sirepo_bluesky/utils/prepare_re_env.py
sirepo_bluesky-0.7.2.dist-info/LICENSE
sirepo_bluesky-0.7.2.dist-info/METADATA
sirepo_bluesky-0.7.2.dist-info/WHEEL
sirepo_bluesky-0.7.2.dist-info/entry_points.txt
sirepo_bluesky-0.7.2.dist-info/top_level.txt
sirepo_bluesky-0.7.2.dist-info/RECORD
