Metadata-Version: 2.1
Name: sirepo-bluesky
Version: 0.7.2
Summary: Sirepo-Bluesky interface
Home-page: https://github.com/NSLS-II/sirepo-bluesky
Author: Brookhaven National Laboratory
Author-email: mrakitin@bnl.gov
License: BSD (3-clause)
Classifier: Development Status :: 2 - Pre-Alpha
Classifier: Natural Language :: English
Classifier: Programming Language :: Python :: 3
Requires-Python: >=3.8
License-File: LICENSE
Requires-Dist: area-detector-handlers
Requires-Dist: bluesky
Requires-Dist: databroker
Requires-Dist: inflection
Requires-Dist: matplotlib
Requires-Dist: numconv
Requires-Dist: numpy
Requires-Dist: ophyd
Requires-Dist: peakutils
Requires-Dist: pymongo
Requires-Dist: pyqt5 >=5.9
Requires-Dist: requests
Requires-Dist: shadow3 >=23.1.4
Requires-Dist: srwpy >=4.0.0b1
Requires-Dist: tfs-pandas
Requires-Dist: unyt
Requires-Dist: xraylib
